README.md
setup.cfg
setup.py
shear/__init__.py
shear.egg-info/PKG-INFO
shear.egg-info/SOURCES.txt
shear.egg-info/dependency_links.txt
shear.egg-info/entry_points.txt
shear.egg-info/top_level.txt