Metadata-Version: 2.1
Name: shear
Version: 0.0.4
Summary: 🐑 Shear: Trim Excess Quotes from your Strings in Python and on the Command Line
Home-page: https://github.com/DanielJDufour/shear
Author: Daniel J. Dufour
Author-email: daniel.j.dufour@gmail.com
License: UNKNOWN
Download-URL: https://github.com/DanielJDufour/shear/tarball/download
Keywords: python,string,unquote
Platform: UNKNOWN
Classifier: Development Status :: 5 - Production/Stable
Classifier: Programming Language :: Python :: 3
Classifier: License :: CC0 1.0 Universal (CC0 1.0) Public Domain Dedication
Classifier: Operating System :: OS Independent
